README.rst
setup.py
bluexpress/connector.py
bluexpress/handler.py
bluexpress/settings.py
django_bluexpress.egg-info/PKG-INFO
django_bluexpress.egg-info/SOURCES.txt
django_bluexpress.egg-info/dependency_links.txt
django_bluexpress.egg-info/requires.txt
django_bluexpress.egg-info/top_level.txt