Metadata-Version: 2.1
Name: django-bluexpress
Version: 1.5.4
Summary: Django Bluexpress Integration
Home-page: https://gitlab.com/linets/ecommerce/oms/integrations/oms-bluexpress/
Author: Linets Development Team
Author-email: dteam@linets.cl
License: MIT
Platform: UNKNOWN
Requires-Python: >=3.7
